{
    "title": "Dot Esports - Esports News, Analysis, Tournament Coverage, and More",
    "url": "dotesports.com",
    "full_url": "https://dotesports.com/",
    "images": [],
    "inputs": [
        {
            "desc": "Search...",
            "type": "search",
            "location": {
                "x": 0,
                "y": 50
            },
            "size": {
                "height": 40,
                "width": 1009
            },
            "position": {
                "horizontal": 0,
                "vertical": -2
            },
            "is_displayed": false
        }
    ],
    "colors": [
        [
            255,
            255,
            255
        ],
        [
            0,
            0,
            0
        ],
        [
            250,
            250,
            250
        ]
    ],
    "desc": "The world leader in esports and competitive gaming coverage, including breaking news, features, analysis, opinion, tournament coverage, and more.",
    "navbar": "LoL\nValorant\nOverwatch\nCS:GO\nDota 2\nCoD\nApex Legends\nPokémon\nMore\nGo Ad-Free\nLogin",
    "text": "Skip to content\nLoL\nValorant\nOverwatch\nCS:GO\nDota 2\nCoD\nApex Legends\nPokémon\nMore\nGo Ad-Free\nLogin\nApex Legends’ season 15 celebrates new player peak—but struggles to compete with seasons past\nAdam Snavely - Dec 7, 2022 4:16 pm\nOverwatch 2 players have come to a decisive verdict on Ramattra after one day\nScott Duwe - Dec 7, 2022 12:10 pm\nBlizzard addresses Overwatch 2 competitive concerns with explanation about mode’s system\nIt's not only you getting placed lower than you expected.\nEthan Garcia - Dec 7, 2022 3:57 pm\nOVERWATCH\nGive it a SEA-pin: Xtreme Gaming completes Dota 2 roster with 2 Malaysian players\nAnother chance at going extreme.\nGökhan Çakır - Dec 7, 2022 2:40 pm\nDOTA 2\nOG to reportedly field second Dota 2 roster with an old theme and at least one TI winner\nOld but gold at least fits the idea.\nCale Michael, Gökhan Çakır - Dec 7, 2022 1:44 pm\nDOTA 2\nQuinn makes the leap, abandons NA for Europe and some Gladiators in 2023 DPC\nThe flame of NA dims ever slightly.\nCale Michael - Dec 7, 2022 12:18 pm\nDOTA 2\nControversial Dota 2 pro set to cash in on transfer rumors after sudden departure\nRumors shape up the roster shuffle season.\nGökhan Çakır, Cale Michael - Dec 7, 2022 12:14 pm\nDOTA 2\nBrazilian CS:GO player slams quality of practice in North America\nWill this ever change?\nLeonardo Biazzi - Dec 7, 2022 8:34 am\nCOUNTER-STRIKE\nUncrowned king steps down: Ame takes time off from Dota 2 as LGD begins huge rebuild\nKeep going! Chunyu.\nGökhan Çakır - Dec 7, 2022 8:27 am\nDOTA 2\nDev1ce breaks silence on Astralis’ early elimination from CS:GO tournament\nIt wasn't what everyone expected from Astralis, but dev1ce seems to be the exact player he was before his medical leave.\nLeonardo Biazzi - Dec 7, 2022 7:43 am\nCOUNTER-STRIKE\nNigma looks for another Miracle, signs ATF for 2023 DPC\nNigma gets a surprising new addition to its roster.\nAnish Nair - Dec 7, 2022 6:36 am\nDOTA 2\nAnubis breaks a historic CS:GO trend 2 weeks after joining the map pool\nBut will it stay that way?\nMateusz Miter - Dec 7, 2022 3:46 am\nCOUNTER-STRIKE\nPosts navigation\nOlder posts\nTrending Articles\nChamber's not alone: Nearly every VALORANT agent receives a change in the 5.12 patch\nScott Robertson - December 2, 2022\nFull TFT Patch 12.23 Set 8 launch notes and updates\nDanny Forster - December 6, 2022\nLiquid acquires World Champion jungler, goes full Korean with revamped LCS roster for 2023\nTyler Esguerra - December 2, 2022\nStay salty: Overwatch 2 devs may have snuck hilarious jab at hero unlock complaints into Battle Pass\nLiz Richardson - December 6, 2022\nHasan banned on Twitch over ‘targeted’ copyright strike, fires salvo at claimant\nAlex Tsiaoussidis - December 6, 2022\n© 2021 Dot Esports",
    "font": "montserrat, sans-serif",
    "buttons": []
}