{
    "title": "Kyoko Shimbun News（虚構新聞社）",
    "url": "kyoko-np.net",
    "full_url": "https://kyoko-np.net/",
    "images": [
        {
            "alt": "虚構新聞",
            "location": {
                "x": 0,
                "y": 24
            },
            "size": {
                "height": 80,
                "width": 277
            },
            "position": {
                "horizontal": -2,
                "vertical": -2
            },
            "is_displayed": true
        },
        {
            "alt": "4コマ",
            "location": {
                "x": 788,
                "y": 1210
            },
            "size": {
                "height": 889,
                "width": 300
            },
            "position": {
                "horizontal": 2,
                "vertical": 2
            },
            "is_displayed": true
        }
    ],
    "inputs": [
        {
            "desc": "検索",
            "type": "text",
            "location": {
                "x": 798,
                "y": 557
            },
            "size": {
                "height": 20,
                "width": 185
            },
            "position": {
                "horizontal": 2,
                "vertical": 0
            },
            "is_displayed": true
        }
    ],
    "colors": [
        [
            255,
            255,
            255
        ],
        [
            250,
            250,
            250
        ],
        [
            235,
            235,
            235
        ]
    ],
    "navbar": "",
    "text": "ピックアップ\n円周率割り切れる\n上上下下左右左右ＢＡ\n自動運転車、運転手置き去り多発\n社会\n政治\n経済\nスポーツ\n国際\n科学\n文化\nエンタメ\nお願い\n「サ終」でも安心　紙製ツイッター配布始まる\nツイッターに大規模障害が起きても、紙に書き込んでツイートできる「ペーパーツイッター」の街頭配布が１日から全国で始まった。米電気自動車大手テスラのイーロン・マスク氏による買収以降、運営をめぐる状況は日々刻々と変化。「サービス終了」という最悪の事態に備えるツイッター利用者らが各地... 続きを読む\n自動運転車に震度７クラスのバイブ装置　滋賀の企業が開発\n伊でスパゲティの絵にスープかける騒ぎ　ネット世論は怒り一色\nレモン２００兆個分の電気　レモン発電所が稼働　愛媛\n青い秋空に「再起動」メッセージ出現　目撃、世界各地で\n額に浮かぶ１２ケタ　マイナンバー焼き印サービスが人気\nバウムクーヘン天日干し\n体内にiPod置き忘れ\n琵琶湖の水ぜんぶ抜く\n人気記事ランキング\n1究極の初心者向け「２マス将棋」発売 愛好家考案\n2「サ終」でも安心 紙製ツイッター配布始まる\n3３本脚の「ヤタガラス」を捕獲、神話裏づけ 島根・出雲産大\n4男性がつり橋から転落 「渡るべからず」看板を無視 京都・黄桜町\n5自動運転車に震度７クラスのバイブ装置 滋賀の企業が開発\n社会\n「サ終」でも安心　紙製ツイッター配布始まる\n青い秋空に「再起動」メッセージ出現　目撃、世界各地で\n額に浮かぶ１２ケタ　マイナンバー焼き印サービスが人気\n駄菓子屋「えびせん１枚５０京円」　１０月値上げ、児童の懐も直撃\n滋賀の夜景、宇宙からみると…　中央に「令和のフロンティア」発見\n政治\n躍進の決め手は「盟神探湯」　若手政治家続々輩出の政治塾\n政府、各種事態見守る「注視庁」設置へ　注視一元化図る\n倍速行動で人生２４０年に　「倍速人生検討委員会」が初会合\n「一億総衆院議員に」　識者、定数１億増０減を提言\n投票用紙に陶片採用　「一票の重み」解消目指す\n経済\n自動運転車に震度７クラスのバイブ装置　滋賀の企業が開発\nローセンス、「脱ツイ廃スマホ」ＤＥＰＨＯＮＥ発表\n電力ひっ迫でも視聴可　ローセンス、「テレビ付きエアコン」初披露\nリニア新幹線、まず大阪へ　米欧経由「東回り」を専門家提案\nＳＤカード、どんどん小さく…　ＩＴ業界、「ステルス値上げ」常態化\nスポーツ\n６連ブロック持ち込みで失格　テトリス世界大会予選\n五輪パラ会場、水の悪臭対策にトイレボール試験投入\n東京五輪、相対的に涼しく　世界中で温室ガス散布実験\n「暴れる猛暑、護摩で調伏」　五輪期間中、祈祷師３千人配置へ\n涼しげな音色で酷暑乗り切れ　新国立競技場に巨大風鈴設置\n国際\n伊でスパゲティの絵にスープかける騒ぎ　ネット世論は怒り一色\n温暖化で沈む「８０８」　南洋諸島・ヤオハチ島の現在\n「石油より安い」米国で万札発電所完成　今冬にも稼働\n有志連合軍、鬼ヶ島に限定豆空爆　負傷鬼多数の情報\n世界最古の酢豚レシピ見つかる　「酢豚パイン論争」に終止符\n科学\nレモン２００兆個分の電気　レモン発電所が稼働　愛媛\n「人間に嫌気」ＡＩ絵師・ＡＩＡＣが引退　活動開始１日で\nサイケ模様の「ヒッピーゼミ」見つかる　５０年以上生存か\n路上の生態系に異変　コロナ禍で追われる軍手のすみか\n宇宙彩る世界最大の花火、開演は５０億年後　世界花火連盟が見通し\n文化\n音楽家の肖像画、今はマイルド　「怖くない音楽室」広がる\n虚構の歴史が現代に根付くメカニズム　偽文書研究『椿井文書』著者に聞く\n神「さい銭届かぬ」　硬貨手数料で合格祈願成就率、過去最低に\n落札直後に刈られた田んぼアート、１８億円で落札\n衛府嵐大、情報商材学部など２学部を新設申請　「稼げる大学」目指す\nエンタメ\n好きな番組ジャンル、首位は「ＣＭ」　報道、バラエティは大きく後退\n七福神きょう仕事納め　全国巡業最終日\n引退宣言のインフルさん、１年ぶり「再起動」発表\n相次ぐタレント降板、本人そっくり「ＣＧ代役」起用検討\n「映画、聞くだけなら１００円」　音漏れ楽しむ「特別室」人気\nお詫び\n「「辛くて苦手」に新商品　「種なし柿の種」登場」についてお詫び（22.03.02）\n「ほのかな甘み　かぼちゃワイン「エル」４月発売」についてお詫び（21.08.19）\n「２ｍのロングバトンも　コロナ禍で「新しい運動会」　マキャベリ小」についてお詫び（20.09.28）\n「ジョン・ケージ「４分３３秒」トリビュート盤発売が決定」についてお詫び（19.01.18）\n「日本の「謙虚」、海外アピールに２００億計上」についてお詫び（17.04.06）\n「シャープ、゜の売却を検討」についてお詫び（15.10.02）\n「フジ、自局専用リモコンを無料配布へ」記事についてお詫び（15.07.21）\n「ウィキペディア書籍化」についてお詫び（15.06.22）\n「次世代炊飯器、ＩＮＦＯＪＡＲ」記事についてお詫び（14.12.20）\n「ステーキさいころ」記事についてお詫び（14.06.25）\n「森永、『グロス』発売」記事についてお詫び（13.07.10）\n「北朝鮮、一方的に勝利宣言」についてお詫び(13.04.16)\n「体罰．ｉｎ」記事についてお詫び(13.02.19)\n広告掲載・執筆依頼\n記事検索\n検索\n虚構新聞社の本\n『虚構新聞 全国版』\n（ジーウォーク／６００円）\nベスト記事収録の完全版。電子版もあります。\n注目コンテンツ\n『ひまわりさん』\n（菅野マナミ／メディアファクトリー）\n最新第12集発売！\n『なめこタイムDX なめよん』\n（Beeworks／エンターブレイン）\nなめこの４コマ、出ました\n『ミガワリメーカー』\n（恩田澄子／講談社）\nおすすめの名作ＳＦです\n虚構漫談\n4コマバックナンバー\n2022年12月7日\n漫画コラム掲載中（6/12更新）\nＲＳＳ／ソーシャル\n虚構新聞社のRSSフィード\n虚構新聞速報／編集部便り\n虚構新聞社Facebook支局\n虚構新聞社ニコニコ支局\n虚構新聞社LINE支局\n虚構新聞のウェブサービス\n公式iOSアプリ\n「虚構新聞」\n公開中\n公式Androidアプリ\n「虚構新聞」\n公開中\n有料メルマガ\n「虚構新聞友の会会報」\n配信中\n音声放送\n「虚構新聞ニュース」\n好評配信中\n友の会会員専用掲示板\n天気\nラダトーム ☁ メルキド ☀ ドムドーラ ☂ マイラ ☁ リムルダール ☁\n交通\n【くら寿司特急】 人身事故のため運行停止中\nマーケット\n円・ドル 100円00銭〜200円00銭\nジンバブエドル 取引停止中\n日経平均 10000円 (-10000円00銭)\n息子を探しています\nごあいさつ\n綱領\n会社概要\n編集部\n広告局\nご意見・ご要望はこちらへ\nこの記事はフィクションであり実在の人物・団体とは関係ありません\nCopyright Kyoko Shimbun.",
    "font": "\"Hiragino Kaku Gothic Pro\", \"ヒラギノ角ゴ Pro W3\", メイリオ, Meiryo, \"ＭＳ Ｐゴシック\", \"Helvetica Neue\", Helvetica, Arial, sans-serif",
    "iframes": [],
    "buttons": [
        {
            "text": "",
            "bg-color": "rgba(239, 239, 239, 1)",
            "location": {
                "x": 0,
                "y": 0
            },
            "size": {
                "height": 42,
                "width": 37
            },
            "position": {
                "horizontal": -2,
                "vertical": -2
            },
            "is_displayed": false
        },
        {
            "text": "検索",
            "bg-color": "rgba(77, 144, 254, 1)",
            "location": {
                "x": 1011,
                "y": 553
            },
            "size": {
                "height": 27,
                "width": 69
            },
            "position": {
                "horizontal": 2,
                "vertical": 0
            },
            "is_displayed": true
        }
    ]
}